Workbook
Name aporte: APP!$C$18
Name Investir_mes: APP!$C$18
Name patrimonio: APP!$C$21
Name ptm_acm: APP!$C$21
Name qtt_anos: APP!$C$19
Name quantidade_anos: APP!$C$19
Name Rendimento_Carteira: APP!$C$13
Name salario: APP!$C$12
Name sus_investimento: APP!$C$14
Name taxa_mensal: APP!$C$20

Sheet APP
B11: CONSIGURAÇÕES
B12: Salário | C12: 2000
B13: Rendimento Carteira | C13: 0.006
B14: Susgestão de Investimento (30%) | C14: =C12*30% -> 600
B17: INVESTIMENTO MENSAL
B18: Quanto investir por mês? | C18: 200
B19: Por quantos anos? | C19: 5
B20: Taxa de rendimento mensal? | C20: 0.01079
B21: Qual o patrimônio acumulado? | C21: =FV(taxa_mensal,qtt_anos*12,aporte*-1) -> 16755.383
B22: Quanto é os dividendos mensais? | C22: =patrimonio*Rendimento_Carteira -> 100.5323
B24: CENÁRIOS | D24: Dividendos
A25: 2 | B25: Quanto em 2 anos? | C25: =FV($C$20,$A25*12,$C$18*-1) -> 5445.5255 | D25: =C25*Rendimento_Carteira -> 32.673153
A26: 5 | B26: Quanto em 5 anos? | C26: =FV($C$20,$A26*12,$C$18*-1) -> 16755.383 | D26: =C26*Rendimento_Carteira -> 100.5323
A27: 10 | B27: Quanto em 10 anos? | C27: =FV($C$20,$A27*12,$C$18*-1) -> 48656.843 | D27: =C27*Rendimento_Carteira -> 291.94106
A28: 20 | B28: Quanto em 20 anos? | C28: =FV($C$20,$A28*12,$C$18*-1) -> 225039.68 | D28: =C28*Rendimento_Carteira -> 1350.2381
A29: 30 | B29: Quanto em 30 anos? | C29: =FV($C$20,$A29*12,$C$18*-1) -> 864433.93 | D29: =C29*Rendimento_Carteira -> 5186.6036
B32: Perfil | C32: Moderado
B33: Valor a ser Investido por Mês | C33: =aporte -> 200
B35: Tipo de FII | C35: Percentual Sugerido | D35: Valores
B36: PAPEL | C36: =VLOOKUP($C$32&"-"&B36,apoio!$A$3:$D$21,4,FALSE) -> 0.32 | D36: =C36*$C$33 -> 64
B37: TIJOLO | C37: =VLOOKUP($C$32&"-"&B37,apoio!$A$3:$D$21,4,FALSE) -> 0.4 | D37: =C37*$C$33 -> 80
B38: HÍBRIDOS | C38: =VLOOKUP($C$32&"-"&B38,apoio!$A$3:$D$21,4,FALSE) -> 0.08 | D38: =C38*$C$33 -> 16
B39: FOF's | C39: =VLOOKUP($C$32&"-"&B39,apoio!$A$3:$D$21,4,FALSE) -> 0.1 | D39: =C39*$C$33 -> 20
B40: DESENVOLVIMENTO | C40: =VLOOKUP($C$32&"-"&B40,apoio!$A$3:$D$21,4,FALSE) -> 0.1 | D40: =C40*$C$33 -> 20
B41: HOTELARIA | C41: =VLOOKUP($C$32&"-"&B41,apoio!$A$3:$D$21,4,FALSE) -> 0.1 | D41: =C41*$C$33 -> 20
D42: =SUM(D36:D41) -> 220

Sheet apoio
A3: CHAVE | B3: Perfil | C3: TIPOS DE FII | D3: %
A4: =B4&"-"&C4 -> Conservador-PAPEL | B4: Conservador | C4: PAPEL | D4: 0.3
A5: =B5&"-"&C5 -> Conservador-TIJOLO | B5: Conservador | C5: TIJOLO | D5: 0.5
A6: =B6&"-"&C6 -> Conservador-HÍBRIDOS | B6: Conservador | C6: HÍBRIDOS | D6: 0.1
A7: =B7&"-"&C7 -> Conservador-FOF's | B7: Conservador | C7: FOF's | D7: 0.1
A8: =B8&"-"&C8 -> Conservador-DESENVOLVIMENTO | B8: Conservador | C8: DESENVOLVIMENTO | D8: 0
A9: =B9&"-"&C9 -> Conservador-HOTELARIA | B9: Conservador | C9: HOTELARIA | D9: 0
A10: =B10&"-"&C10 -> Moderado-PAPEL | B10: Moderado | C10: PAPEL | D10: 0.32
A11: =B11&"-"&C11 -> Moderado-TIJOLO | B11: Moderado | C11: TIJOLO | D11: 0.4
A12: =B12&"-"&C12 -> Moderado-HÍBRIDOS | B12: Moderado | C12: HÍBRIDOS | D12: 0.08
A13: =B13&"-"&C13 -> Moderado-FOF's | B13: Moderado | C13: FOF's | D13: 0.1
A14: =B14&"-"&C14 -> Moderado-DESENVOLVIMENTO | B14: Moderado | C14: DESENVOLVIMENTO | D14: 0.1
A15: =B15&"-"&C15 -> Moderado-HOTELARIA | B15: Moderado | C15: HOTELARIA | D15: 0.1
... A21: =B21&"-"&C21 -> Agressivo-HOTELARIA | B21: Agressivo | C21: HOTELARIA | D21: 0.1
